canvas_painter.cp313-win_amd64.pyd
sfml-graphics-2.dll
sfml-system-2.dll
sfml-window-2.dll
canvas_painter-1.0.2.dist-info/METADATA
canvas_painter-1.0.2.dist-info/WHEEL
canvas_painter-1.0.2.dist-info/top_level.txt
canvas_painter-1.0.2.dist-info/RECORD
