Metadata-Version: 2.4
Name: canvas-painter
Version: 1.0.2
Summary: Canvas is a simple Python graphics library using SFML.
Author-email: Vasu Jayendra <vasujayendra57@gmail.com>
License: MIT
Requires-Python: >=3.8
